EasyBlogger-3.1.3.dist-info/DESCRIPTION.rst
EasyBlogger-3.1.3.dist-info/METADATA
EasyBlogger-3.1.3.dist-info/RECORD
EasyBlogger-3.1.3.dist-info/WHEEL
EasyBlogger-3.1.3.dist-info/entry_points.txt
EasyBlogger-3.1.3.dist-info/metadata.json
EasyBlogger-3.1.3.dist-info/top_level.txt
blogger/__init__.py
blogger/blogger.py
blogger/main.py
