Metadata-Version: 2.0
Name: EasyBlogger
Version: 3.1.3
Summary: A (very) easy CLI interface to Blogger blogs
Home-page: https://github.com/raghur/easyblogger
Author: Raghu Rajagopalan
Author-email: raghu.nospam@gmail.com
License: BSD
Keywords: blogger,cli,markdown,asciidoc
Platform: UNKNOWN
Classifier: Development Status :: 5 - Production/Stable
Classifier: Topic :: Utilities
Classifier: Topic :: Internet :: WWW/HTTP :: Site Management
Classifier: License :: OSI Approved :: BSD License
Classifier: Programming Language :: Python :: 3
Classifier: Programming Language :: Python :: 3.5
Classifier: Programming Language :: Python :: 3.6
Requires-Dist: pypandoc
Requires-Dist: google-api-python-client
Requires-Dist: oauth2client
Requires-Dist: python-gflags
Requires-Dist: httplib2
Requires-Dist: toml
Requires-Dist: gevent
Requires-Dist: coloredlogs
Requires-Dist: pyyaml
Requires-Dist: chardet
